noisyenv/__init__.py
noisyenv/wrappers.py
tests/__init__.py
tests/test_wrappers.py
noisyenv-0.1.1.dist-info/LICENSE
noisyenv-0.1.1.dist-info/METADATA
noisyenv-0.1.1.dist-info/WHEEL
noisyenv-0.1.1.dist-info/top_level.txt
noisyenv-0.1.1.dist-info/RECORD
