Metadata-Version: 2.1
Name: noisyenv
Version: 0.1.1
Summary: Simple noisy environment augmentation for reinforcement learning
Home-page: https://github.com/UCL-IFT/noisyenv
Author: Raad Khraishi
Author-email: raad.khraishi@ucl.ac.uk
Classifier: Development Status :: 3 - Alpha
Classifier: Intended Audience :: Developers
Classifier: License :: OSI Approved :: MIT License
Classifier: Programming Language :: Python :: 3.7
Classifier: Programming Language :: Python :: 3.8
Classifier: Programming Language :: Python :: 3.9
Classifier: Programming Language :: Python :: 3.10
Classifier: Programming Language :: Python :: 3.11
License-File: LICENSE
Requires-Dist: gymnasium (>=0.26.1)
Requires-Dist: numpy (>=1.21.6)
